mentat_sdk/__init__.py
mentat_sdk/client.py
mentat_sdk/commands/__init__.py
mentat_sdk/commands/handler.py
mentat_sdk/commands/model.py
mentat_sdk/config/__init__.py
mentat_sdk/config/manager.py
mentat_sdk/logger.py
mentat_sdk/notifications/__init__.py
mentat_sdk/notifications/manager.py
mentat_sdk/notifications/model.py
mentat_sdk/utils/__init__.py
mentat_sdk/utils/uuid_generator.py
mentat_sdk/websocket/__init__.py
mentat_sdk/websocket/connection.py
mentat_sdk/websocket/exceptions.py
mentat_sdk/websocket/message_parser.py
mentat_sdk-0.1.1.dist-info/METADATA
mentat_sdk-0.1.1.dist-info/WHEEL
mentat_sdk-0.1.1.dist-info/RECORD
