Metadata-Version: 2.1
Name: mentat-sdk
Version: 0.1.1
Summary: Python SDK for interacting with the Mentat agent
License: MIT
Author: Mentat team
Author-email: ylan@mentat.sh
Requires-Python: >=3.9,<4.0
Classifier: Development Status :: 4 - Beta
Classifier: Intended Audience :: Developers
Classifier: License :: OSI Approved :: MIT License
Classifier: Programming Language :: Python :: 3
Classifier: Programming Language :: Python :: 3.9
Classifier: Programming Language :: Python :: 3.10
Classifier: Programming Language :: Python :: 3.11
Classifier: Programming Language :: Python :: 3.12
Requires-Dist: coloredlogs (>=15.0.1,<16.0.0)
Requires-Dist: websocket-client (>=1.7.0,<2.0.0)
